cf_clus/__init__.py
cf_clus/interaction_views.py
cf_clus/library.py
cf_clus/settings.py
cf_clus/urls.py
cf_clus/utils.py
cf_clus/views.py
cf_clus/visualization_views.py
cf_clus/bin/Clus.jar
cf_clus/bin/LICENSE.txt
cf_clus/bin/README.txt
cf_clus/package_data/categories/55c0628f-f12d-40fe-bbca-f7c960654a01.json
cf_clus/package_data/widgets/03bbb6f0-90d3-4a04-bf11-7982df67f379.json
cf_clus/package_data/widgets/087086f2-be89-4c9e-a110-261efc5acf7f.json
cf_clus/package_data/widgets/8716ff1a-ef07-431c-b552-bbb7ffd64b90.json
cf_clus/package_data/widgets/be2f33c3-f2af-4bd1-ad0e-42dbe9c590f8.json
cf_clus/package_data/widgets/e86563eb-e893-401b-92b4-4477d5e8cd49.json
cf_clus/package_data/widgets/fd638c01-e814-4f24-b431-f306424f5383.json
cf_clus/static/cf_clus/icons/treeview/TreeVisualization.png
cf_clus/static/cf_clus/icons/treeview/construction_work .png
cf_clus/static/cf_clus/icons/widget/TreeVisualization.png
cf_clus/static/cf_clus/icons/widget/construction_work .png
cf_clus/templates/interactions/.gitdirectory
cf_clus/templates/visualizations/.gitdirectory
cf_clus/templates/visualizations/cf_clus_display_svg_tree.html
cf_clus/templates/visualizations/cf_clus_display_tree.html
cf_clus/templates/visualizations/cf_clus_display_tree_and_examples.html
cf_clus/templates/visualizations/cf_clus_display_tree_and_summary.html
cf_clus-1.0.4.dist-info/DESCRIPTION.rst
cf_clus-1.0.4.dist-info/METADATA
cf_clus-1.0.4.dist-info/RECORD
cf_clus-1.0.4.dist-info/WHEEL
cf_clus-1.0.4.dist-info/metadata.json
cf_clus-1.0.4.dist-info/top_level.txt
