Metadata-Version: 2.0
Name: cf-clus
Version: 1.0.4
Summary: Induce predictive clustering trees in ClowdFlows.
Home-page: https://github.com/xflows/cf_clus
Author: Janez Kranjc
Author-email: janez.kranjc@gmail.com
License: GPL
Platform: UNKNOWN
Classifier: Development Status :: 5 - Production/Stable
Classifier: Intended Audience :: Developers
Classifier: Intended Audience :: Science/Research
Requires-Dist: liac-arff
